{
  "formatVersion": 1,
  "database": {
    "version": 2,
    "identityHash": "c0272c36277934e81f9f9a910174dcd9",
    "entities": [
      {
        "tableName": "Profile",
        "createSql": "CREATE TABLE IF NOT EXISTS `${TABLE_NAME}` (`id` INTEGER PRIMARY KEY AUTOINCREMENT NOT NULL, `address` TEXT NOT NULL, `avatar` TEXT, `isBanned` INTEGER NOT NULL, `bio` TEXT, `birthDate` TEXT, `createdAt` INTEGER, `emails` TEXT, `firstName` TEXT NOT NULL, `lastName` TEXT NOT NULL, `gender` TEXT)",
        "fields": [
          {
            "fieldPath": "id",
            "columnName": "id",
            "affinity": "INTEGER",
            "notNull": true
          },
          {
            "fieldPath": "address",
            "columnName": "address",
            "affinity": "TEXT",
            "notNull": true
          },
          {
            "fieldPath": "avatar",
            "columnName": "avatar",
            "affinity": "TEXT",
            "notNull": false
          },
          {
            "fieldPath": "isBanned",
            "columnName": "isBanned",
            "affinity": "INTEGER",
            "notNull": true
          },
          {
            "fieldPath": "bio",
            "columnName": "bio",
            "affinity": "TEXT",
            "notNull": false
          },
          {
            "fieldPath": "birthDate",
            "columnName": "birthDate",
            "affinity": "TEXT",
            "notNull": false
          },
          {
            "fieldPath": "createdAt",
            "columnName": "createdAt",
            "affinity": "INTEGER",
            "notNull": false
          },
          {
            "fieldPath": "emails",
            "columnName": "emails",
            "affinity": "TEXT",
            "notNull": false
          },
          {
            "fieldPath": "firstName",
            "columnName": "firstName",
            "affinity": "TEXT",
            "notNull": true
          },
          {
            "fieldPath": "lastName",
            "columnName": "lastName",
            "affinity": "TEXT",
            "notNull": true
          },
          {
            "fieldPath": "gender",
            "columnName": "gender",
            "affinity": "TEXT",
            "notNull": false
          }
        ],
        "primaryKey": {
          "columnNames": [
            "id"
          ],
          "autoGenerate": true
        },
        "indices": [],
        "foreignKeys": []
      },
      {
        "tableName": "PDV",
        "createSql": "CREATE TABLE IF NOT EXISTS `${TABLE_NAME}` (`id` INTEGER PRIMARY KEY AUTOINCREMENT NOT NULL, `address` TEXT, `type` TEXT NOT NULL, `domain` TEXT, `engine` TEXT, `query` TEXT, `timestamp` TEXT, `avatar` TEXT, `bio` TEXT, `birthday` TEXT, `emails` TEXT, `firstName` TEXT, `lastName` TEXT, `gender` TEXT)",
        "fields": [
          {
            "fieldPath": "id",
            "columnName": "id",
            "affinity": "INTEGER",
            "notNull": true
          },
          {
            "fieldPath": "address",
            "columnName": "address",
            "affinity": "TEXT",
            "notNull": false
          },
          {
            "fieldPath": "type",
            "columnName": "type",
            "affinity": "TEXT",
            "notNull": true
          },
          {
            "fieldPath": "domain",
            "columnName": "domain",
            "affinity": "TEXT",
            "notNull": false
          },
          {
            "fieldPath": "engine",
            "columnName": "engine",
            "affinity": "TEXT",
            "notNull": false
          },
          {
            "fieldPath": "query",
            "columnName": "query",
            "affinity": "TEXT",
            "notNull": false
          },
          {
            "fieldPath": "timestamp",
            "columnName": "timestamp",
            "affinity": "TEXT",
            "notNull": false
          },
          {
            "fieldPath": "avatar",
            "columnName": "avatar",
            "affinity": "TEXT",
            "notNull": false
          },
          {
            "fieldPath": "bio",
            "columnName": "bio",
            "affinity": "TEXT",
            "notNull": false
          },
          {
            "fieldPath": "birthday",
            "columnName": "birthday",
            "affinity": "TEXT",
            "notNull": false
          },
          {
            "fieldPath": "emails",
            "columnName": "emails",
            "affinity": "TEXT",
            "notNull": false
          },
          {
            "fieldPath": "firstName",
            "columnName": "firstName",
            "affinity": "TEXT",
            "notNull": false
          },
          {
            "fieldPath": "lastName",
            "columnName": "lastName",
            "affinity": "TEXT",
            "notNull": false
          },
          {
            "fieldPath": "gender",
            "columnName": "gender",
            "affinity": "TEXT",
            "notNull": false
          }
        ],
        "primaryKey": {
          "columnNames": [
            "id"
          ],
          "autoGenerate": true
        },
        "indices": [],
        "foreignKeys": []
      }
    ],
    "views": [],
    "setupQueries": [
      "CREATE TABLE IF NOT EXISTS room_master_table (id INTEGER PRIMARY KEY,identity_hash TEXT)",
      "INSERT OR REPLACE INTO room_master_table (id,identity_hash) VALUES(42, 'c0272c36277934e81f9f9a910174dcd9')"
    ]
  }
}